scripts/__init__.py
scripts/main.py
comic_list-0.2.dist-info/LICENSE
comic_list-0.2.dist-info/METADATA
comic_list-0.2.dist-info/WHEEL
comic_list-0.2.dist-info/entry_points.txt
comic_list-0.2.dist-info/top_level.txt
comic_list-0.2.dist-info/RECORD
