Metadata-Version: 2.1
Name: comic-list
Version: 0.2
Summary: Outputs list of missing comic book issue files in a folder given a range
Home-page: https://github.com/nateify/comic-list
Author: nateify
Author-email: nateify@users.noreply.github.com
License: UNKNOWN
Platform: UNKNOWN
Classifier: Programming Language :: Python :: 3
Classifier: License :: OSI Approved :: MIT License
Classifier: Operating System :: OS Independent
Requires-Python: >=3.2
